csptlib/__init__.py
csptlib/datastore.py
csptlib/getdata.py
csptlib/transplotlib.py
csptlib/main/__init__.py
csptlib/main/main_External_Data.py
csptlib/main/main_Vissim.py
csptlib/main/tests.py
csptlib/systrajectorylib/__init__.py
csptlib/systrajectorylib/ratedata.py
csptlib/systrajectorylib/rateperformance.py
csptlib-1.4.dist-info/LICENSE
csptlib-1.4.dist-info/METADATA
csptlib-1.4.dist-info/WHEEL
csptlib-1.4.dist-info/top_level.txt
csptlib-1.4.dist-info/RECORD
